dbuanime.py
dbuanime-0.0.1.dist-info/WHEEL
dbuanime-0.0.1.dist-info/METADATA
dbuanime-0.0.1.dist-info/RECORD
