Metadata-Version: 2.1
Name: dbuanime
Version: 0.0.1
Summary: Поиск Аниме/Манги по: Жанру,Рандому,Топу по годам.
Author: DarsoX
Author-email: darsox.anime@gmail.com
Requires-Python: >=3.6,<4.0
Classifier: Programming Language :: Python :: 3
Classifier: Programming Language :: Python :: 3.6
Classifier: Programming Language :: Python :: 3.7
Classifier: Programming Language :: Python :: 3.8
Classifier: Programming Language :: Python :: 3.9
